clsregistry/__init__.py
clsregistry/clsregistry.py
clsregistry/clsregistry_multi.py
clsregistry-0.1.0.dist-info/LICENSE
clsregistry-0.1.0.dist-info/METADATA
clsregistry-0.1.0.dist-info/WHEEL
clsregistry-0.1.0.dist-info/top_level.txt
clsregistry-0.1.0.dist-info/RECORD
